Metadata-Version: 2.1
Name: drmanagement
Version: 0.1
Summary: An all in one tool for data scientists and project managers to analyze, visualize the project status
Home-page: UNKNOWN
Author: Team Dr.pinnacle
Author-email: nandanr094@gmail.com
License: UNKNOWN
Platform: UNKNOWN
Requires-Python: >=3.6
